{"name":"searching_by_keyword_laptop_should_display_the_corresponding_article","id":"org.example.features.search.SearchByKeywordStory:searching_by_keyword_laptop_should_display_the_corresponding_article","testCaseName":"org.example.features.search.SearchByKeywordStory","testSteps":[{"number":1,"description":"Is the home page","duration":4115,"startTime":"2024-05-12T20:11:53.957503900+03:00[Europe/Bucharest]","screenshots":[{"screenshot":"a7d4a5eaa672bdd50f485a009a5db9cc8faccdb6dc5b43e9d14ccba328bc2811.png","timeStamp":1715533918073}],"result":"SUCCESS","precondition":false,"level":0},{"number":2,"description":"Looks for: laptop","duration":2122,"startTime":"2024-05-12T20:11:58.079721100+03:00[Europe/Bucharest]","screenshots":[{"screenshot":"3fb3a7d65cbb22c5f012a22a51cc55a4dee8546c7b6053d5de7224febed0fcba.png","timeStamp":1715533920202}],"result":"SUCCESS","precondition":false,"level":0,"children":[{"number":3,"description":"Enters: laptop","duration":697,"startTime":"2024-05-12T20:11:58.082723200+03:00[Europe/Bucharest]","screenshots":[{"screenshot":"2f22c70665a586d4b74200df0249075ab99c080f75c57604f8c2afe1f437ecd1.png","timeStamp":1715533918779}],"result":"SUCCESS","precondition":false,"level":1},{"number":4,"description":"Starts search","duration":1419,"startTime":"2024-05-12T20:11:58.780920600+03:00[Europe/Bucharest]","screenshots":[{"screenshot":"2f22c70665a586d4b74200df0249075ab99c080f75c57604f8c2afe1f437ecd1.png","timeStamp":1715533918784},{"screenshot":"3fb3a7d65cbb22c5f012a22a51cc55a4dee8546c7b6053d5de7224febed0fcba.png","timeStamp":1715533920200}],"result":"SUCCESS","precondition":false,"level":1}]},{"number":5,"description":"Should see definition: A laptop computer.","duration":377,"startTime":"2024-05-12T20:12:00.202345+03:00[Europe/Bucharest]","screenshots":[{"screenshot":"3fb3a7d65cbb22c5f012a22a51cc55a4dee8546c7b6053d5de7224febed0fcba.png","timeStamp":1715533920579}],"result":"SUCCESS","precondition":false,"level":0}],"userStory":{"id":"org.example.features.search.SearchByKeywordStory","storyName":"Search by keyword story","storyClassName":"org.example.features.search.SearchByKeywordStory","path":"search","type":"story"},"featureTag":{"name":"Search/Search by keyword story","type":"story","displayName":"Search/Search by keyword story"},"title":"Searching by keyword laptop should display the corresponding article","tags":[{"name":"Search","type":"feature","displayName":"Search"},{"name":"Search/Search by keyword story","type":"story","displayName":"Search by keyword story"},{"name":"Search","type":"capability","displayName":"Search for definitions"}],"startTime":"2024-05-12T20:11:53.645777700+03:00[Europe/Bucharest]","duration":6937,"projectKey":"","sessionId":"46de30797dadf5bf31c5041808f248d9","driver":"chrome","isManualTestingUpToDate":false,"manual":false,"testSource":"JUnit","order":0,"result":"SUCCESS"}